{
  "1": {
    "month": "Сәуір",
    "subjects": ["Ағылшын", "Қазақ тілі", "Дене шынықтыру", "Қазақстан тарих", "Алгебра", "Биология", "География"],
    "homework": [

    ],
    "absentees": ["Арайлым", "Қалима ⚠️", "Ұлдана"]
  },
  "2": {
    "month": "Сәуір",
    "subjects": ["Құқық негіздері", "Қазақ тілі", "Информатика", "Химия", "Алгебра", "Биология", "Физика"],
    "homework": [
        "",
        "7-тапсырма 168-бет",
        "",
        "",
        "№27.3",
        "§45 түсінік"
],
    "absentees": ["Гүлназым", "Қалима ⚠️", "Ұлболсын"]
  },
  "3": {
    "month": "Сәуір",
    "subjects": ["Ағылшын", "Қазақ әдебиеті", "Геометрия", "Дене шынықтыру", "Орыс тілі", "Дүниежүзі тарихы", "Жаһандық құзыреттер"],
    "homework": [
        "Ex:3 on P92",
        ""],
    "absentees": ["Әлия", "Қалима ⚠️"]
  },
  "4": {
    "month": "Сәуір",
    "subjects": ["Ағылшын", "Көркем еңбек", "Қазақ әдебиеті", "Орыс тілі", "Химия", "Биология", "Абайтану"],
    "homework": [
        "",
        "",
        "Фариза Оңғарсынованың бір өлеңін мәнерлеп оқу",
        "«Смерть поэта» поэзисынан 8 қатар жаттау 242-бет",
        "1-ден 14-ке дейінгі барлық тапсырмаларды орныдау 88-бет"
    ],
    "absentees": ["Әлия", "Бейбіт", "Гүлназым", "Қалима ⚠️", "Ұлболсын"]
  },
  "5": {
    "month": "Сәуір",
    "subjects": [],
    "homework": [],
    "absentees": []
  },
  "6": {
    "month": "Сәуір",
    "subjects": [],
    "homework": [],
    "absentees": []
  },
  "7": {
    "month": "Сәуір",
    "subjects": ["Тәрбие сағат", "География", "Орыс тілі", "Қазақстан тарих", "Алгебра", "Дене шынықтыру", "Физика"],
    "homework": [
        "",
        "§47 тесттерін орындау",
        "«Мать Тереза» оқу және зерттеу",
        "§47 параграфтан 4 сұрақ жазу"
    ],
    "absentees": ["Әлия", "Ұлболсын ⚠️"]
  },
  "8": {
    "month": "Сәуір",
    "subjects": ["Ағылшын", "Қазақ тілі", "Дене шынықтыру", "Қазақстан тарих", "Алгебра", "Биология", "География"],
    "homework": [
        "Ex:3 on P95",
        "6-тапсырма 171-бет",
        "",
        "§48 түсінік",
        "",
        "",
        "§48 түсінік"
    ],
    "absentees": []
  },
  "9": {
    "month": "Сәуір",
    "subjects": ["Құқық негіздері", "Қазақ тілі", "Информатика", "Химия", "Алгебра", "Биология", "Физика"],
    "homework": [
        "",
        "6-тапсырма 174-бет",
        "§5.1 оқу және түсіну",
        "§50-51 оқу және түсіну",
        "",
        "§47 түсінік",
        "§33 түсінік"
    ],
    "absentees": []
  },
  "10": {
    "month": "Сәуір",
    "subjects": ["Ағылшын", "Қазақ әдебиеті", "Геометрия", "Дене шынықтыру", "Орыс тілі", "Дүниежүзі тарихы", "Жаһандық құзыреттер"],
    "homework": [
        "Ex:5 on P97",
        "",
        "",
        "",
        "246-247 беттегі өлеңнен үзінді жаттау",
        "§25 түсінік",
        "§27 конспект аяқтау"
    ],
    "absentees": []
  },
  "11": {
    "month": "Сәуір",
    "subjects": ["Ағылшын", "Көркем еңбек", "Қазақ әдебиеті", "Орыс тілі", "Химия", "Биология", "Абайтану"],
    "homework": [
        "",
        "",
        "",
        "",
        ""
    ],
    "absentees": []
  },
  "12": {
    "month": "Сәуір",
    "subjects": [],
    "homework": [],
    "absentees": []
  },
  "13": {
    "month": "Сәуір",
    "subjects": [],
    "homework": [],
    "absentees": []
  },
  "14": {
    "month": "Сәуір",
    "subjects": ["Тәрбие сағат", "География", "Орыс тілі", "Қазақстан тарих", "Алгебра", "Дене шынықтыру", "Физика"],
    "homework": [
        "",
        "§49 түсінік",
        "",
        "§48 түсінік"
    ],
    "absentees": []
  },
  "15": {
    "month": "Сәуір",
    "subjects": ["Ағылшын", "Қазақ тілі", "Дене шынықтыру", "Қазақстан тарих", "Алгебра", "Биология", "География"],
    "homework": [
        "",
        "",
        "",
        "",
        "",
        "",
        ""
    ],
    "absentees": []
  }
}